telegram_bot/__init__.py
telegram_bot/config/__init__.py
telegram_bot/config/telegram_send_config.py
telegram_bot/core/__init__.py
telegram_bot/core/interfaces/__init__.py
telegram_bot/core/interfaces/base_sender.py
telegram_bot/core/single_tone/__init__.py
telegram_bot/core/single_tone/service.py
telegram_bot/errors/__init__.py
telegram_bot/errors/telegram_send_error.py
telegram_bot/senders/__init__.py
telegram_bot/senders/document_sender.py
telegram_bot/senders/media_group_sender.py
telegram_bot/senders/text_sender.py
telegram_bot/services/__init__.py
telegram_bot/services/base/__init__.py
telegram_bot/services/base/base_telegram_sender.py
telegram_bot/services/mixin/__init__.py
telegram_bot/services/mixin/telegram_sender_mixin.py
telegram_bot/services/telegram_document_sender.py
telegram_bot/services/telegram_media_group_sender.py
telegram_bot/services/telegram_text_sender.py
telegram_bot/utiles/__init__.py
telegram_bot/utiles/format_base_header_message.py
telegram_bot/utiles/get_logger.py
telm_bot-0.0.2.dist-info/LICENSE
telm_bot-0.0.2.dist-info/METADATA
telm_bot-0.0.2.dist-info/WHEEL
telm_bot-0.0.2.dist-info/RECORD
