Metadata-Version: 2.3
Name: telm-bot
Version: 0.0.2
Summary: A Python package for building Telegram bots using python-telegram-bot with Tor support.
License: SEE LICENSE FILE
Author: minjun ju
Author-email: dev.mjun@gmail.com
Requires-Python: >=3.10,<4.0
Classifier: License :: Other/Proprietary License
Classifier: Programming Language :: Python :: 3
Classifier: Programming Language :: Python :: 3.10
Classifier: Programming Language :: Python :: 3.11
Classifier: Programming Language :: Python :: 3.12
Classifier: Programming Language :: Python :: 3.13
Classifier: Programming Language :: Python :: 3 :: Only
Requires-Dist: dotenv (>=0.9.9,<0.10.0)
Requires-Dist: pydantic (>=2.11.4,<3.0.0)
Requires-Dist: python-telegram-bot (>=22.1,<23.0)
Requires-Dist: tenacity (>=9.1.2,<10.0.0)
